shadeDB/__init__.py
shadeDB/cli.py
shadeDB/config.py
shadeDB/core.py
shadeDB/exceptions.py
shadeDB/schedule.py
shadeDB/service.py
shadedb-0.2.5.dist-info/licenses/LICENSE
shadedb-0.2.5.dist-info/METADATA
shadedb-0.2.5.dist-info/WHEEL
shadedb-0.2.5.dist-info/entry_points.txt
shadedb-0.2.5.dist-info/top_level.txt
shadedb-0.2.5.dist-info/RECORD
