Metadata-Version: 2.4
Name: shadeDB
Version: 0.2.5
Summary: A lightweight, class-oriented database server with a CLI wrapper for instant querying on any device.Store, update, fetch, and remove structured data with a single command. Designed for speed and simplicity, it’s perfect for embedded systems, mobile devices, developer tools, and quick local services.
Author: Shade
Author-email: adesolasherifdeen3@gmail.com
License: MIT
Project-URL: GitHub, https://github.com/harkerbyte
Project-URL: Facebook, https://facebook.com/harkerbyte
Project-URL: Whatsapp, https://whatsapp.com/channel/0029Vb5f98Z90x2p6S1rhT0S
Project-URL: Youtube, https://youtube.com/@harkerbyte
Project-URL: Instagram, https://instagram.com/harkerbyte
Classifier: Programming Language :: Python :: 3
Classifier: License :: OSI Approved :: MIT License
Classifier: Environment :: Console
Classifier: Intended Audience :: Developers
Classifier: Topic :: Database :: Database Engines/Servers
Requires-Python: >=3.8
License-File: LICENSE
Dynamic: author
Dynamic: author-email
Dynamic: classifier
Dynamic: description
Dynamic: description-content-type
Dynamic: license
Dynamic: license-file
Dynamic: project-url
Dynamic: requires-python
Dynamic: summary
